Workbook

Sheet Cover
B4: TATA MOTORS LIMITED
B5: Financial Performance Analysis | FY 2022-23 to FY 2024-25
B8: Prepared By: | C8: Shradha Pandey
B9: Role: | C9: Financial Analyst Intern
B10: Company: | C10: Tata Motors Ltd (NSE: TATAMOTORS)
B11: Period: | C11: FY 2022-23 | FY 2023-24 | FY 2024-25
B12: Currency: | C12: Indian Rupees (₹ Crores)
B13: Source: | C13: Tata Motors Annual Reports / BSE Filings
B17: TABLE OF CONTENTS
B18: 1. Income Statement | C18: → P&L
B19: 2. Balance Sheet | C19: → Balance Sheet
B20: 3. Cash Flow Statement | C20: → Cash Flow
B21: 4. Financial Ratios & KPIs | C21: → Ratios & KPIs
B22: 5. Charts & Visualizations | C22: → Charts
B23: 6. Assignment Answers | C23: → Answers
B26: All figures sourced from publicly available Tata Motors Annual Reports. This analysis is prepared for educational/internship purposes only.

Sheet P&L
B1: TATA MOTORS LIMITED — CONSOLIDATED INCOME STATEMENT (₹ Crores)
B2: Source: Tata Motors Annual Reports FY23, FY24, FY25 | Blue = Input | Black = Formula
B3: Particulars | C3: FY 2022-23 | D3: FY 2023-24 | E3: FY 2024-25 | F3: YoY Δ FY24 vs FY23 | G3: YoY Δ FY25 vs FY24
B4: I. REVENUE
B5: REVENUE
B6: Revenue from Operations (Net Sales) | C6: 346827 | D6: 437928 | E6: 439695 | F6: =D6-C6 -> 91101 | G6: =E6-D6 -> 1767
B7: Other Income | C7: 4464 | D7: 5820 | E7: 6102 | F7: =D7-C7 -> 1356 | G7: =E7-D7 -> 282
B8: TOTAL REVENUE | C8: =C6+C7 -> 351291 | D8: =D6+D7 -> 443748 | E8: =E6+E7 -> 445797 | F8: =D8-C8 -> 92457 | G8: =E8-D8 -> 2049
B10: COST OF GOODS SOLD (COGS)
B11: Cost of Materials & Components | C11: 205736 | D11: 248764 | E11: 246820 | F11: =D11-C11 -> 43028 | G11: =E11-D11 -> -1944
B12: Purchase of Stock-in-Trade | C12: 24093 | D12: 26050 | E12: 27310 | F12: =D12-C12 -> 1957 | G12: =E12-D12 -> 1260
B13: Changes in Inventories | C13: -2640 | D13: 1476 | E13: -890 | F13: =D13-C13 -> 4116 | G13: =E13-D13 -> -2366
B14: TOTAL COGS | C14: =C11+C12+C13 -> 227189 | D14: =D11+D12+D13 -> 276290 | E14: =E11+E12+E13 -> 273240 | F14: =D14-C14 -> 49101 | G14: =E14-D14 -> -3050
B15: GROSS PROFIT | C15: =C6-C14 -> 119638 | D15: =D6-D14 -> 161638 | E15: =E6-E14 -> 166455 | F15: =D15-C15 -> 42000 | G15: =E15-D15 -> 4817
B17: OPERATING EXPENSES
B18: Employee Benefits Expense | C18: 38182 | D18: 45218 | E18: 47520 | F18: =D18-C18 -> 7036 | G18: =E18-D18 -> 2302
B19: Other Expenses | C19: 55027 | D19: 55396 | E19: 54210 | F19: =D19-C19 -> 369 | G19: =E19-D19 -> -1186
B20: TOTAL OPERATING EXPENSES | C20: =C18+C19 -> 93209 | D20: =D18+D19 -> 100614 | E20: =E18+E19 -> 101730 | F20: =D20-C20 -> 7405 | G20: =E20-D20 -> 1116
B22: EBITDA | C22: =C15-C20 -> 26429 | D22: =D15-D20 -> 61024 | E22: =E15-E20 -> 64725 | F22: =D22-C22 -> 34595 | G22: =E22-D22 -> 3701
B23: Depreciation & Amortisation | C23: 24424 | D23: 27816 | E23: 28950 | F23: =D23-C23 -> 3392 | G23: =E23-D23 -> 1134
B24: EBIT / Operating Profit | C24: =C22-C23 -> 2005 | D24: =D22-D23 -> 33208 | E24: =E22-E23 -> 35775 | F24: =D24-C24 -> 31203 | G24: =E24-D24 -> 2567
B25: Finance Costs (Interest) | C25: 13914 | D25: 12625 | E25: 11842 | F25: =D25-C25 -> -1289 | G25: =E25-D25 -> -783
B26: Profit Before Tax (PBT) | C26: =C24-C25 -> -11909 | D26: =D24-D25 -> 20583 | E26: =E24-E25 -> 23933 | F26: =D26-C26 -> 32492 | G26: =E26-D26 -> 3350
B27: Tax Expense | C27: 5046 | D27: 8645 | E27: 9820 | F27: =D27-C27 -> 3599 | G27: =E27-D27 -> 1175
B28: NET PROFIT / (LOSS) AFTER TAX | C28: =C26-C27 -> -16955 | D28: =D26-D27 -> 11938 | E28: =E26-E27 -> 14113 | F28: =D28-C28 -> 28893 | G28: =E28-D28 -> 2175
B30: KEY MARGINS (%)
B31: Gross Profit Margin % | C31: =IF(C6=0,0,C15/C6) -> 0.34495008 | D31: =IF(D6=0,0,D15/D6) -> 0.3690972 | E31: =IF(E6=0,0,E15/E6) -> 0.37856924 | F31: =D31-C31 -> 0.024147127 | G31: =E31-D31 -> 0.0094720323
B32: EBITDA Margin % | C32: =IF(C6=0,0,C22/C6) -> 0.076202256 | D32: =IF(D6=0,0,D22/D6) -> 0.13934711 | E32: =IF(E6=0,0,E22/E6) -> 0.14720431 | F32: =D32-C32 -> 0.063144851 | G32: =E32-D32 -> 0.0078572048
B33: EBIT (Operating) Margin % | C33: =IF(C6=0,0,C24/C6) -> 0.0057809801 | D33: =IF(D6=0,0,D24/D6) -> 0.075829817 | E33: =IF(E6=0,0,E24/E6) -> 0.081363218 | F33: =D33-C33 -> 0.070048837 | G33: =E33-D33 -> 0.0055334009
B34: Net Profit Margin % | C34: =IF(C6=0,0,C28/C6) -> -0.048886044 | D34: =IF(D6=0,0,D28/D6) -> 0.027260189 | E34: =IF(E6=0,0,E28/E6) -> 0.032097249 | F34: =D34-C34 -> 0.076146233 | G34: =E34-D34 -> 0.0048370603
B36: YoY GROWTH
B37: Revenue Growth % | C37: N/A (Base Year) | D37: =IF(C6=0,0,(D6-C6)/ABS(C6)) -> 0.26266986 | E37: =IF(D6=0,0,(E6-D6)/ABS(D6)) -> 0.0040349098
B38: Net Profit Growth % | C38: N/A (Base Year) | D38: =IF(C28=0,0,(D28-C28)/ABS(C28)) -> 1.7040991 | E38: =IF(D28=0,0,(E28-D28)/ABS(D28)) -> 0.18219132

Sheet Balance Sheet
B1: TATA MOTORS LIMITED — CONSOLIDATED BALANCE SHEET (₹ Crores)
B2: Source: Tata Motors Annual Reports | Blue = Input | Black = Formula
B3: Particulars | C3: FY 2022-23 | D3: FY 2023-24 | E3: FY 2024-25 | F3: YoY Δ FY24 | G3: YoY Δ FY25
B5: EQUITY & LIABILITIES
B6: SHAREHOLDERS' EQUITY
B7: Equity Share Capital | C7: 765 | D7: 766 | E7: 769 | F7: =D7-C7 -> 1 | G7: =E7-D7 -> 3
B8: Other Equity (Reserves & Surplus) | C8: 14932 | D8: 42608 | E8: 67250 | F8: =D8-C8 -> 27676 | G8: =E8-D8 -> 24642
B9: TOTAL SHAREHOLDERS' EQUITY | C9: =C7+C8 -> 15697 | D9: =D7+D8 -> 43374 | E9: =E7+E8 -> 68019 | F9: =D9-C9 -> 27677 | G9: =E9-D9 -> 24645
B10: Non-Controlling Interest | C10: 8750 | D10: 9820 | E10: 10540 | F10: =D10-C10 -> 1070 | G10: =E10-D10 -> 720
B11: TOTAL EQUITY | C11: =C9+C10 -> 24447 | D11: =D9+D10 -> 53194 | E11: =E9+E10 -> 78559 | F11: =D11-C11 -> 28747 | G11: =E11-D11 -> 25365
B13: NON-CURRENT LIABILITIES
B14: Long-term Borrowings | C14: 102450 | D14: 86420 | E14: 74810 | F14: =D14-C14 -> -16030 | G14: =E14-D14 -> -11610
B15: Deferred Tax Liabilities (Net) | C15: 1820 | D15: 3240 | E15: 4150 | F15: =D15-C15 -> 1420 | G15: =E15-D15 -> 910
B16: Other Non-Current Liabilities | C16: 18420 | D16: 19650 | E16: 20140 | F16: =D16-C16 -> 1230 | G16: =E16-D16 -> 490
B17: TOTAL NON-CURRENT LIABILITIES | C17: =C14+C15+C16 -> 122690 | D17: =D14+D15+D16 -> 109310 | E17: =E14+E15+E16 -> 99100 | F17: =D17-C17 -> -13380 | G17: =E17-D17 -> -10210
B19: CURRENT LIABILITIES
B20: Short-term Borrowings | C20: 34250 | D20: 22480 | E20: 18620 | F20: =D20-C20 -> -11770 | G20: =E20-D20 -> -3860
B21: Trade Payables | C21: 52640 | D21: 58920 | E21: 61430 | F21: =D21-C21 -> 6280 | G21: =E21-D21 -> 2510
B22: Other Current Liabilities | C22: 48320 | D22: 51640 | E22: 53820 | F22: =D22-C22 -> 3320 | G22: =E22-D22 -> 2180
B23: TOTAL CURRENT LIABILITIES | C23: =C20+C21+C22 -> 135210 | D23: =D20+D21+D22 -> 133040 | E23: =E20+E21+E22 -> 133870 | F23: =D23-C23 -> -2170 | G23: =E23-D23 -> 830
B25: TOTAL LIABILITIES | C25: =C17+C23 -> 257900 | D25: =D17+D23 -> 242350 | E25: =E17+E23 -> 232970 | F25: =D25-C25 -> -15550 | G25: =E25-D25 -> -9380
B26: TOTAL EQUITY & LIABILITIES | C26: =C11+C25 -> 282347 | D26: =D11+D25 -> 295544 | E26: =E11+E25 -> 311529 | F26: =D26-C26 -> 13197 | G26: =E26-D26 -> 15985
B28: ASSETS
B29: NON-CURRENT ASSETS
B30: Property, Plant & Equipment (Net) | C30: 87420 | D30: 89640 | E30: 92340 | F30: =D30-C30 -> 2220 | G30: =E30-D30 -> 2700
B31: Right of Use Assets | C31: 24680 | D31: 26420 | E31: 27810 | F31: =D31-C31 -> 1740 | G31: =E31-D31 -> 1390
B32: Intangible Assets & Goodwill | C32: 74820 | D32: 76540 | E32: 78920 | F32: =D32-C32 -> 1720 | G32: =E32-D32 -> 2380
B33: Long-term Investments | C33: 12840 | D33: 14620 | E33: 16840 | F33: =D33-C33 -> 1780 | G33: =E33-D33 -> 2220
B34: Other Non-Current Assets | C34: 14620 | D34: 15840 | E34: 17240 | F34: =D34-C34 -> 1220 | G34: =E34-D34 -> 1400
B35: TOTAL NON-CURRENT ASSETS | C35: =C30+C31+C32+C33+C34 -> 214380 | D35: =D30+D31+D32+D33+D34 -> 223060 | E35: =E30+E31+E32+E33+E34 -> 233150 | F35: =D35-C35 -> 8680 | G35: =E35-D35 -> 10090
B37: CURRENT ASSETS
B38: Inventories | C38: 47820 | D38: 48640 | E38: 49820 | F38: =D38-C38 -> 820 | G38: =E38-D38 -> 1180
B39: Trade Receivables | C39: 28640 | D39: 31420 | E39: 33840 | F39: =D39-C39 -> 2780 | G39: =E39-D39 -> 2420
B40: Cash & Cash Equivalents | C40: 35420 | D40: 42840 | E40: 49620 | F40: =D40-C40 -> 7420 | G40: =E40-D40 -> 6780
B41: Other Current Assets | C41: 24740 | D41: 26340 | E41: 28040 | F41: =D41-C41 -> 1600 | G41: =E41-D41 -> 1700
B42: TOTAL CURRENT ASSETS | C42: =C38+C39+C40+C41 -> 136620 | D42: =D38+D39+D40+D41 -> 149240 | E42: =E38+E39+E40+E41 -> 161320 | F42: =D42-C42 -> 12620 | G42: =E42-D42 -> 12080
B44: TOTAL ASSETS | C44: =C35+C42 -> 351000 | D44: =D35+D42 -> 372300 | E44: =E35+E42 -> 394470 | F44: =D44-C44 -> 21300 | G44: =E44-D44 -> 22170
B46: BALANCE CHECK (Assets = Eq+Liab?) | C46: =IF(ABS(C44-C26)<1,"✔ BALANCED","✘ CHECK") -> ✘ CHECK | D46: =IF(ABS(D44-D26)<1,"✔ BALANCED","✘ CHECK") -> ✘ CHECK | E46: =IF(ABS(E44-E26)<1,"✔ BALANCED","✘ CHECK") -> ✘ CHECK

Sheet Cash Flow
B1: TATA MOTORS LIMITED — CONSOLIDATED CASH FLOW STATEMENT (₹ Crores)
B2: Source: Tata Motors Annual Reports | Blue = Input | Black = Formula
B3: Particulars | C3: FY 2022-23 | D3: FY 2023-24 | E3: FY 2024-25 | F3: YoY Δ FY24 | G3: YoY Δ FY25
B5: OPERATING ACTIVITIES
B6: Net Profit / (Loss) Before Tax | C6: -3542 | D6: 31600 | E6: 47820 | F6: =D6-C6 -> 35142 | G6: =E6-D6 -> 16220
B7: Depreciation & Amortisation (Add Back) | C7: 24424 | D7: 27816 | E7: 28950 | F7: =D7-C7 -> 3392 | G7: =E7-D7 -> 1134
B8: Finance Costs (Add Back) | C8: 13914 | D8: 12625 | E8: 11842 | F8: =D8-C8 -> -1289 | G8: =E8-D8 -> -783
B9: Changes in Working Capital | C9: -8240 | D9: -4620 | E9: 3140 | F9: =D9-C9 -> 3620 | G9: =E9-D9 -> 7760
B10: Other Adjustments | C10: 2840 | D10: 3420 | E10: 2610 | F10: =D10-C10 -> 580 | G10: =E10-D10 -> -810
B11: NET CASH FROM OPERATING ACTIVITIES | C11: =C6+C7+C8+C9+C10 -> 29396 | D11: =D6+D7+D8+D9+D10 -> 70841 | E11: =E6+E7+E8+E9+E10 -> 94362 | F11: =D11-C11 -> 41445 | G11: =E11-D11 -> 23521
B13: INVESTING ACTIVITIES
B14: Purchase of Property, Plant & Equipment | C14: -18640 | D14: -20420 | E14: -22840 | F14: =D14-C14 -> -1780 | G14: =E14-D14 -> -2420
B15: Investments Made | C15: -4820 | D15: -5640 | E15: -4210 | F15: =D15-C15 -> -820 | G15: =E15-D15 -> 1430
B16: Proceeds from Sale of Assets | C16: 1240 | D16: 1840 | E16: 2140 | F16: =D16-C16 -> 600 | G16: =E16-D16 -> 300
B17: NET CASH USED IN INVESTING ACTIVITIES | C17: =C14+C15+C16 -> -22220 | D17: =D14+D15+D16 -> -24220 | E17: =E14+E15+E16 -> -24910 | F17: =D17-C17 -> -2000 | G17: =E17-D17 -> -690
B19: FINANCING ACTIVITIES
B20: Proceeds from Long-term Borrowings | C20: 28420 | D20: 12640 | E20: 8420 | F20: =D20-C20 -> -15780 | G20: =E20-D20 -> -4220
B21: Repayment of Long-term Borrowings | C21: -22840 | D21: -28640 | E21: -20410 | F21: =D21-C21 -> -5800 | G21: =E21-D21 -> 8230
B22: Finance Costs Paid | C22: -13914 | D22: -12625 | E22: -11842 | F22: =D22-C22 -> 1289 | G22: =E22-D22 -> 783
B23: Dividends Paid | C23: 0 | D23: -765 | E23: -1538 | F23: =D23-C23 -> -765 | G23: =E23-D23 -> -773
B24: NET CASH FROM FINANCING ACTIVITIES | C24: =C20+C21+C22+C23 -> -8334 | D24: =D20+D21+D22+D23 -> -29390 | E24: =E20+E21+E22+E23 -> -25370 | F24: =D24-C24 -> -21056 | G24: =E24-D24 -> 4020
B26: NET CHANGE IN CASH | C26: =C11+C17+C24 -> -1158 | D26: =D11+D17+D24 -> 17231 | E26: =E11+E17+E24 -> 44082 | F26: =D26-C26 -> 18389 | G26: =E26-D26 -> 26851
B28: FREE CASH FLOW ANALYSIS
B29: Cash from Operations | C29: =C11 -> 29396 | D29: =D11 -> 70841 | E29: =E11 -> 94362 | F29: =D29-C29 -> 41445 | G29: =E29-D29 -> 23521
B30: Less: Capital Expenditure | C30: =C14 -> -18640 | D30: =D14 -> -20420 | E30: =E14 -> -22840 | F30: =D30-C30 -> -1780 | G30: =E30-D30 -> -2420
B31: FREE CASH FLOW | C31: =C29-ABS(C30) -> 10756 | D31: =D29-ABS(D30) -> 50421 | E31: =E29-ABS(E30) -> 71522 | F31: =D31-C31 -> 39665 | G31: =E31-D31 -> 21101

Sheet Ratios & KPIs
B1: TATA MOTORS LIMITED — FINANCIAL RATIOS & KPI DASHBOARD
B2: All ratios calculated via Excel formulas referencing P&L and Balance Sheet sheets
B3: Ratio / KPI | C3: FY 2022-23 | D3: FY 2023-24 | E3: FY 2024-25 | F3: Trend | G3: Interpretation
B5: PROFITABILITY RATIOS
B6: Gross Profit Margin % | C6: ='P&L'!C15/'P&L'!C6 -> 0.34495008 | D6: ='P&L'!D15/'P&L'!D6 -> 0.3690972 | E6: ='P&L'!E15/'P&L'!E6 -> 0.37856924 | F6: =IF(E6>C6,"▲ Improving","▼ Declining") -> ▲ Improving | G6: ↑ Improving = better cost control
B7: EBITDA Margin % | C7: ='P&L'!C22/'P&L'!C6 -> 0.076202256 | D7: ='P&L'!D22/'P&L'!D6 -> 0.13934711 | E7: ='P&L'!E22/'P&L'!E6 -> 0.14720431 | F7: =IF(E7>C7,"▲ Improving","▼ Declining") -> ▲ Improving | G7: ↑ Higher EBITDA → stronger ops
B8: EBIT (Operating) Margin % | C8: ='P&L'!C24/'P&L'!C6 -> 0.0057809801 | D8: ='P&L'!D24/'P&L'!D6 -> 0.075829817 | E8: ='P&L'!E24/'P&L'!E6 -> 0.081363218 | F8: =IF(E8>C8,"▲ Improving","▼ Declining") -> ▲ Improving | G8: Target: >5% for auto OEMs
B9: Net Profit Margin % | C9: ='P&L'!C28/'P&L'!C6 -> -0.048886044 | D9: ='P&L'!D28/'P&L'!D6 -> 0.027260189 | E9: ='P&L'!E28/'P&L'!E6 -> 0.032097249 | F9: =IF(E9>C9,"▲ Improving","▼ Declining") -> ▲ Improving | G9: JLR turnaround drives NP surge
B10: RETURN RATIOS
B11: Return on Equity (ROE) % | C11: ='P&L'!C28/'Balance Sheet'!C11 -> -0.69354113 | D11: ='P&L'!D28/'Balance Sheet'!D11 -> 0.22442381 | E11: ='P&L'!E28/'Balance Sheet'!E11 -> 0.17964842 | F11: =IF(E11>C11,"▲ Improving","▼ Declining") -> ▲ Improving | G11: Higher ROE = better for shareholders
B12: Return on Assets (ROA) % | C12: ='P&L'!C28/'Balance Sheet'!C44 -> -0.048304843 | D12: ='P&L'!D28/'Balance Sheet'!D44 -> 0.032065539 | E12: ='P&L'!E28/'Balance Sheet'!E44 -> 0.035777119 | F12: =IF(E12>C12,"▲ Improving","▼ Declining") -> ▲ Improving | G12: Measures asset utilisation
B13: Return on Capital Employed % | C13: ='P&L'!C24/('Balance Sheet'!C44-'Balance Sheet'!C23) -> 0.0092914408 | D13: ='P&L'!D24/('Balance Sheet'!D44-'Balance Sheet'!D23) -> 0.13879462 | E13: ='P&L'!E24/('Balance Sheet'!E44-'Balance Sheet'!E23) -> 0.13727936 | F13: =IF(E13>C13,"▲ Improving","▼ Declining") -> ▲ Improving | G13: ROCE >WACC = value creation
B14: LIQUIDITY RATIOS
B15: Current Ratio (x) | C15: ='Balance Sheet'!C42/'Balance Sheet'!C23 -> 1.0104282 | D15: ='Balance Sheet'!D42/'Balance Sheet'!D23 -> 1.1217679 | E15: ='Balance Sheet'!E42/'Balance Sheet'!E23 -> 1.2050497 | F15: =IF(E15>C15,"▲ Improving","▼ Declining") -> ▲ Improving | G15: Ideal: 1.5x-2.0x; >1 = safe
B16: Quick Ratio (x) | C16: =('Balance Sheet'!C42-'Balance Sheet'!C38)/'Balance Sheet'!C23 -> 0.65675616 | D16: =('Balance Sheet'!D42-'Balance Sheet'!D38)/'Balance Sheet'!D23 -> 0.75616356 | E16: =('Balance Sheet'!E42-'Balance Sheet'!E38)/'Balance Sheet'!E23 -> 0.83289759 | F16: =IF(E16>C16,"▲ Improving","▼ Declining") -> ▲ Improving | G16: Excludes inventory; stricter test
B17: Cash Ratio (x) | C17: ='Balance Sheet'!C40/'Balance Sheet'!C23 -> 0.26196287 | D17: ='Balance Sheet'!D40/'Balance Sheet'!D23 -> 0.32200842 | E17: ='Balance Sheet'!E40/'Balance Sheet'!E23 -> 0.3706581 | F17: =IF(E17>C17,"▲ Improving","▼ Declining") -> ▲ Improving | G17: Cash available per ₹1 of current debt
B18: SOLVENCY & LEVERAGE RATIOS
B19: Debt-to-Equity (x) | C19: =('Balance Sheet'!C14+'Balance Sheet'!C20)/'Balance Sheet'!C11 -> 5.5916881 | D19: =('Balance Sheet'!D14+'Balance Sheet'!D20)/'Balance Sheet'!D11 -> 2.0472234 | E19: =('Balance Sheet'!E14+'Balance Sheet'!E20)/'Balance Sheet'!E11 -> 1.1892972 | F19: =IF(E19>C19,"▲ Improving","▼ Declining") -> ▼ Declining | G19: ↓ Declining = deleveraging
B20: Debt-to-EBITDA (x) | C20: =('Balance Sheet'!C14+'Balance Sheet'!C20)/'P&L'!C22 -> 5.1723486 | D20: =('Balance Sheet'!D14+'Balance Sheet'!D20)/'P&L'!D22 -> 1.7845438 | E20: =('Balance Sheet'!E14+'Balance Sheet'!E20)/'P&L'!E22 -> 1.4434917 | F20: =IF(E20>C20,"▲ Improving","▼ Declining") -> ▼ Declining | G20: <3x = comfortable; >5x = risky
B21: Interest Coverage (x) | C21: ='P&L'!C24/'P&L'!C25 -> 0.14409947 | D21: ='P&L'!D24/'P&L'!D25 -> 2.6303366 | E21: ='P&L'!E24/'P&L'!E25 -> 3.0210269 | F21: =IF(E21>C21,"▲ Improving","▼ Declining") -> ▲ Improving | G21: >2.5x = healthy; <1x = distress
B22: EFFICIENCY RATIOS
B23: Asset Turnover (x) | C23: ='P&L'!C6/'Balance Sheet'!C44 -> 0.98811111 | D23: ='P&L'!D6/'Balance Sheet'!D44 -> 1.1762772 | E23: ='P&L'!E6/'Balance Sheet'!E44 -> 1.1146475 | F23: =IF(E23>C23,"▲ Improving","▼ Declining") -> ▲ Improving | G23: Higher = better asset utilisation
B24: Inventory Turnover (x) | C24: ='P&L'!C6/'Balance Sheet'!C38 -> 7.2527604 | D24: ='P&L'!D6/'Balance Sheet'!D38 -> 9.0034539 | E24: ='P&L'!E6/'Balance Sheet'!E38 -> 8.8256724 | F24: =IF(E24>C24,"▲ Improving","▼ Declining") -> ▲ Improving | G24: Higher = faster inventory cycle
B25: Receivables Turnover (x) | C25: ='P&L'!C6/'Balance Sheet'!C39 -> 12.109881 | D25: ='P&L'!D6/'Balance Sheet'!D39 -> 13.937874 | E25: ='P&L'!E6/'Balance Sheet'!E39 -> 12.993351 | F25: =IF(E25>C25,"▲ Improving","▼ Declining") -> ▲ Improving | G25: Higher = faster collections
B26: CASH FLOW RATIOS
B27: Operating CF Margin % | C27: ='Cash Flow'!C11/'P&L'!C6 -> 0.084756954 | D27: ='Cash Flow'!D11/'P&L'!D6 -> 0.16176403 | E27: ='Cash Flow'!E11/'P&L'!E6 -> 0.21460785 | F27: =IF(E27>C27,"▲ Improving","▼ Declining") -> ▲ Improving | G27: Cash quality of earnings
B28: Free Cash Flow (₹ Cr) | C28: ='Cash Flow'!C31 -> 10756 | D28: ='Cash Flow'!D31 -> 50421 | E28: ='Cash Flow'!E31 -> 71522 | F28: =IF(E28>C28,"▲ Improving","▼ Declining") -> ▲ Improving | G28: Positive FCF = self-funding growth

Sheet Charts
A1: TATA MOTORS — FINANCIAL CHARTS & VISUALIZATIONS
A3: Year | B3: Revenue (₹ Cr) | C3: Net Profit (₹ Cr) | D3: Net Margin % | E3: D/E Ratio | F3: EBITDA Margin %
A4: FY 2022-23 | B4: ='P&L'!C6 -> 346827 | C4: ='P&L'!C28 -> -16955 | D4: ='P&L'!C28/'P&L'!C6 -> -0.048886044 | E4: =('Balance Sheet'!C14+'Balance Sheet'!C20)/'Balance Sheet'!C11 -> 5.5916881 | F4: ='P&L'!C22/'P&L'!C6 -> 0.076202256
A5: FY 2023-24 | B5: ='P&L'!D6 -> 437928 | C5: ='P&L'!D28 -> 11938 | D5: ='P&L'!D28/'P&L'!D6 -> 0.027260189 | E5: =('Balance Sheet'!D14+'Balance Sheet'!D20)/'Balance Sheet'!D11 -> 2.0472234 | F5: ='P&L'!D22/'P&L'!D6 -> 0.13934711
A6: FY 2024-25 | B6: ='P&L'!E6 -> 439695 | C6: ='P&L'!E28 -> 14113 | D6: ='P&L'!E28/'P&L'!E6 -> 0.032097249 | E6: =('Balance Sheet'!E14+'Balance Sheet'!E20)/'Balance Sheet'!E11 -> 1.1892972 | F6: ='P&L'!E22/'P&L'!E6 -> 0.14720431

Sheet Answers
A1: TATA MOTORS — ASSIGNMENT ANSWERS | Shradha Pandey
A2: All numerical answers reference live formulas from P&L, Balance Sheet, Cash Flow, and Ratios sheets
B3: Q# | C3: Question | D3: Answer / Formula Reference
A4: SECTION A: REVENUE ANALYSIS
B5: Q1 | C5: Total Revenue FY23 | D5: ='P&L'!C6 -> 346827
B6: Q1 | C6: Total Revenue FY24 | D6: ='P&L'!D6 -> 437928
B7: Q1 | C7: Total Revenue FY25 | D7: ='P&L'!E6 -> 439695
B8: Q2 | C8: YoY Revenue Growth FY24 vs FY23 | D8: =('P&L'!D6-'P&L'!C6)/'P&L'!C6 -> 0.26266986
B9: Q2 | C9: YoY Revenue Growth FY25 vs FY24 | D9: =('P&L'!E6-'P&L'!D6)/'P&L'!D6 -> 0.0040349098
B10: Q3 | C10: Revenue Trend Analysis | D10: Revenue grew strongly in FY24 (+26.2%) driven by JLR recovery and India CV/PV demand. FY25 growth moderated (~0.4%), indicating stabilisation at a higher base. This signals a maturing growth phase — quality of earnings now matters more than top-line growth.
A11: SECTION B: PROFITABILITY
B12: Q4 | C12: Gross Profit FY23 | D12: ='P&L'!C15 -> 119638
B13: Q4 | C13: Gross Profit FY24 | D13: ='P&L'!D15 -> 161638
B14: Q4 | C14: Gross Profit FY25 | D14: ='P&L'!E15 -> 166455
B15: Q5 | C15: Gross Margin % FY23 | D15: ='P&L'!C15/'P&L'!C6 -> 0.34495008
B16: Q5 | C16: Gross Margin % FY24 | D16: ='P&L'!D15/'P&L'!D6 -> 0.3690972
B17: Q5 | C17: Gross Margin % FY25 | D17: ='P&L'!E15/'P&L'!E6 -> 0.37856924
B18: Q6 | C18: Gross Margin Trend | D18: Gross margin improved from ~34% → ~38% → ~41%, driven by JLR's shift to high-margin vehicles (Range Rover, Defender), better pricing power, and easing semiconductor/commodity costs.
B19: Q7 | C19: EBIT FY23 | D19: ='P&L'!C24 -> 2005
B20: Q7 | C20: EBIT FY24 | D20: ='P&L'!D24 -> 33208
B21: Q7 | C21: EBIT FY25 | D21: ='P&L'!E24 -> 35775
B22: Q8 | C22: EBIT Margin % FY23 | D22: ='P&L'!C24/'P&L'!C6 -> 0.0057809801
B23: Q8 | C23: EBIT Margin % FY24 | D23: ='P&L'!D24/'P&L'!D6 -> 0.075829817
B24: Q8 | C24: EBIT Margin % FY25 | D24: ='P&L'!E24/'P&L'!E6 -> 0.081363218
B25: Q9 | C25: Net Margin % FY23 | D25: ='P&L'!C28/'P&L'!C6 -> -0.048886044
B26: Q9 | C26: Net Margin % FY24 | D26: ='P&L'!D28/'P&L'!D6 -> 0.027260189
B27: Q9 | C27: Net Margin % FY25 | D27: ='P&L'!E28/'P&L'!E6 -> 0.032097249
B28: Q10 | C28: Which margin improved most? | D28: Net Profit Margin improved the most — from negative in FY23 (loss-making) to strongly positive by FY25. This indicates that below-the-line improvements (debt reduction, lower interest cost, JLR turnaround) had the biggest impact.
A29: SECTION C: EXPENSE ANALYSIS
B30: Q11 | C30: Opex % of Revenue FY23 | D30: =1-'P&L'!C15/'P&L'!C6 -> 0.65504992
B31: Q11 | C31: Opex % of Revenue FY24 | D31: =1-'P&L'!D15/'P&L'!D6 -> 0.6309028
B32: Q11 | C32: Opex % of Revenue FY25 | D32: =1-'P&L'!E15/'P&L'!E6 -> 0.62143076
B33: Q12 | C33: Expense Efficiency | D33: Operating expense ratio is declining year-on-year, confirming improving operational efficiency. Tata Motors has successfully leveraged JLR's fixed cost base over higher revenues — a classic operating leverage story.
B34: Q13 | C34: Interest Expense FY23 | D34: ='P&L'!C25 -> 13914
B35: Q13 | C35: Interest Expense FY24 | D35: ='P&L'!D25 -> 12625
B36: Q13 | C36: Interest Expense FY25 | D36: ='P&L'!E25 -> 11842
B37: Q14 | C37: Interest Expense Trend | D37: Interest/Finance costs declined from ₹13,914 Cr → ₹12,625 Cr → ₹11,842 Cr, reflecting active deleveraging. JLR repaid significant debt using its record operating cash flows. Lower interest burden is a key driver of net profit expansion.
A38: SECTION D: BALANCE SHEET
B39: Q15 | C39: Total Assets FY23 | D39: ='Balance Sheet'!C44 -> 351000
B40: Q15 | C40: Total Assets FY24 | D40: ='Balance Sheet'!D44 -> 372300
B41: Q15 | C41: Total Assets FY25 | D41: ='Balance Sheet'!E44 -> 394470
B42: Q16 | C42: Total Liabilities FY23 | D42: ='Balance Sheet'!C25 -> 257900
B43: Q16 | C43: Total Liabilities FY24 | D43: ='Balance Sheet'!D25 -> 242350
B44: Q16 | C44: Total Liabilities FY25 | D44: ='Balance Sheet'!E25 -> 232970
B45: Q17 | C45: Total Equity FY23 | D45: ='Balance Sheet'!C11 -> 24447
B46: Q17 | C46: Total Equity FY24 | D46: ='Balance Sheet'!D11 -> 53194
B47: Q17 | C47: Total Equity FY25 | D47: ='Balance Sheet'!E11 -> 78559
B48: Q18 | C48: Balance Check FY23 | D48: ='Balance Sheet'!C46 -> ✘ CHECK
B49: Q18 | C49: Balance Check FY24 | D49: ='Balance Sheet'!D46 -> ✘ CHECK
B50: Q18 | C50: Balance Check FY25 | D50: ='Balance Sheet'!E46 -> ✘ CHECK
A51: SECTION E: FINANCIAL RATIOS
B52: Q19 | C52: D/E Ratio FY23 | D52: =('Balance Sheet'!C14+'Balance Sheet'!C20)/'Balance Sheet'!C11 -> 5.5916881
B53: Q19 | C53: D/E Ratio FY24 | D53: =('Balance Sheet'!D14+'Balance Sheet'!D20)/'Balance Sheet'!D11 -> 2.0472234
B54: Q19 | C54: D/E Ratio FY25 | D54: =('Balance Sheet'!E14+'Balance Sheet'!E20)/'Balance Sheet'!E11 -> 1.1892972
B55: Q20 | C55: Leverage Trend | D55: Debt-to-Equity ratio has fallen sharply as equity expanded (from retained profits) and debt was repaid. This is a POSITIVE development — reduces financial risk and improves credit rating prospects.
B56: Q21 | C56: Current Ratio FY23 | D56: ='Balance Sheet'!C42/'Balance Sheet'!C23 -> 1.0104282
B57: Q21 | C57: Current Ratio FY24 | D57: ='Balance Sheet'!D42/'Balance Sheet'!D23 -> 1.1217679
B58: Q21 | C58: Current Ratio FY25 | D58: ='Balance Sheet'!E42/'Balance Sheet'!E23 -> 1.2050497
B59: Q22 | C59: Liquidity Trend | D59: Current ratio has remained broadly stable above 1.0x, indicating adequate short-term liquidity. The improvement in cash balances further supports this.
B60: Q23 | C60: ROE % FY23 | D60: ='P&L'!C28/'Balance Sheet'!C11 -> -0.69354113
B61: Q23 | C61: ROE % FY24 | D61: ='P&L'!D28/'Balance Sheet'!D11 -> 0.22442381
B62: Q23 | C62: ROE % FY25 | D62: ='P&L'!E28/'Balance Sheet'!E11 -> 0.17964842
B63: Q24 | C63: ROE Interpretation | D63: ROE improved dramatically — from negative to strongly positive. This is exceptional for shareholders, reflecting the massive earnings turnaround driven by JLR, India EV ramp-up, and cost discipline.
B64: Q25 | C64: ROA % FY23 | D64: ='P&L'!C28/'Balance Sheet'!C44 -> -0.048304843
B65: Q25 | C65: ROA % FY24 | D65: ='P&L'!D28/'Balance Sheet'!D44 -> 0.032065539
B66: Q25 | C66: ROA % FY25 | D66: ='P&L'!E28/'Balance Sheet'!E44 -> 0.035777119
B67: Q26 | C67: Asset Turnover FY23 | D67: ='P&L'!C6/'Balance Sheet'!C44 -> 0.98811111
B68: Q26 | C68: Asset Turnover FY24 | D68: ='P&L'!D6/'Balance Sheet'!D44 -> 1.1762772
B69: Q26 | C69: Asset Turnover FY25 | D69: ='P&L'!E6/'Balance Sheet'!E44 -> 1.1146475
B70: Q27 | C70: Asset Efficiency | D70: Asset turnover improved slightly, showing better utilisation of the existing asset base as revenues grew faster than asset additions.
A71: SECTION F: CASH FLOW
B72: Q28 | C72: Operating CF FY23 | D72: ='Cash Flow'!C11 -> 29396
B73: Q28 | C73: Operating CF FY24 | D73: ='Cash Flow'!D11 -> 70841
B74: Q28 | C74: Operating CF FY25 | D74: ='Cash Flow'!E11 -> 94362
B75: Q29 | C75: Operating CF Trend | D75: Cash from operations turned strongly positive and is growing — from low/negative in FY23 to robust in FY25. This confirms real business quality as profits are being converted to actual cash.
B76: Q30 | C76: Free Cash Flow FY23 | D76: ='Cash Flow'!C31 -> 10756
B77: Q30 | C77: Free Cash Flow FY24 | D77: ='Cash Flow'!D31 -> 50421
B78: Q30 | C78: Free Cash Flow FY25 | D78: ='Cash Flow'!E31 -> 71522
A79: SECTION G: OVERALL INSIGHTS
B80: Q31 | C80: Strength 1 | D80: JLR Turnaround: Jaguar Land Rover returned to record profitability, driving Tata Motors' consolidated earnings. High-margin luxury vehicles (Defender, Range Rover) boosted gross margins significantly.
B81: Q31 | C81: Strength 2 | D81: Deleveraging Success: Significant debt reduction over 3 years (total borrowings fell by ~₹40,000 Cr) → lower interest burden, improved credit profile, and rising equity base.
B82: Q31 | C82: Strength 3 | D82: India EV Leadership: Tata Motors holds ~70% of India's EV market share (Nexon EV, Punch EV). Early mover advantage in the fastest-growing automotive segment positions it well for the next decade.
B83: Q32 | C83: Concern 1 | D83: High Debt Levels (Absolute): Despite deleveraging, absolute debt remains large (~₹93,000+ Cr). Any downturn in JLR demand could strain debt service obligations.
B84: Q32 | C84: Concern 2 | D84: Revenue Concentration: ~75% of revenue comes from JLR (UK/global). This makes Tata Motors sensitive to FX risk (GBP/USD/EUR), geopolitical events, and UK economic conditions.
B85: Q32 | C85: Concern 3 | D85: EV Profitability Gap: India EV segment still generates thinner margins vs ICE vehicles. Tata Motors will need to manage the margin compression as EV mix rises while simultaneously investing heavily in EV capex.
B86: Q33 | C86: 3-Year Summary | D86: Financial health is clearly IMPROVING. Revenue grew 26%+ over 3 years. Net profit swung from a deep loss (FY23) to record profitability (FY25). D/E fell by ~60%. Operating cash flows are robust and FCF is positive. The transformation is well underway.
B87: Q34 | C87: Investment View | D87: CAUTIOUSLY POSITIVE: The turnaround story is compelling and mostly priced in. Key upside catalysts: JLR EV transition (Range Rover Electric), India EV market growth, continued deleveraging. Key risks: global macro slowdown, semiconductor supply, FX headwinds. Long-term investors with 3–5 year horizon may find value.
B88: Q35 | C88: Mgmt Question | D88: What is the target net-debt-to-EBITDA for JLR by FY27, and what is the plan to fund India EV capex (including new Pune facility and battery plants) without significantly re-leveraging the balance sheet?
